ursabot/__init__.py
ursabot/auth.py
ursabot/builders.py
ursabot/changes.py
ursabot/cli.py
ursabot/commands.py
ursabot/configs.py
ursabot/docker.py
ursabot/formatters.py
ursabot/hooks.py
ursabot/master.py
ursabot/reporters.py
ursabot/schedulers.py
ursabot/secrets.py
ursabot/steps.py
ursabot/utils.py
ursabot/workers.py
ursabot/tests/__init__.py
ursabot/tests/conftest.py
ursabot/tests/mocks.py
ursabot/tests/test_builders.py
ursabot/tests/test_changes.py
ursabot/tests/test_commands.py
ursabot/tests/test_docker.py
ursabot/tests/test_formatters.py
ursabot/tests/test_hooks.py
ursabot/tests/test_master.py
ursabot/tests/test_reporters.py
ursabot/tests/test_steps.py
ursabot/tests/test_utils.py
ursabot/tests/test_workers.py
ursabot-0.1.0.dist-info/LICENSE
ursabot-0.1.0.dist-info/LICENSE_BSD
ursabot-0.1.0.dist-info/METADATA
ursabot-0.1.0.dist-info/WHEEL
ursabot-0.1.0.dist-info/entry_points.txt
ursabot-0.1.0.dist-info/top_level.txt
ursabot-0.1.0.dist-info/RECORD
