Metadata-Version: 2.1
Name: ursabot
Version: 0.1.0
Summary: Extension for the Buildbot continuous integration tool
Home-page: http://github.com/ursa-labs/ursabot
Maintainer: Ursa-Labs team
Maintainer-email: team@ursalabs.org
License: UNKNOWN
Keywords: ursabot,buildbot,ci,continuous-integration
Platform: UNKNOWN
Requires-Python: >=3.6
Requires-Dist: buildbot-console-view
Requires-Dist: buildbot-grid-view
Requires-Dist: buildbot-waterfall-view
Requires-Dist: buildbot-worker
Requires-Dist: buildbot-www
Requires-Dist: buildbot
Requires-Dist: click
Requires-Dist: distro
Requires-Dist: docker-map
Requires-Dist: docker
Requires-Dist: dockerpty
Requires-Dist: python-dotenv
Requires-Dist: ruamel.yaml
Requires-Dist: tabulate
Requires-Dist: toolz
Requires-Dist: toposort
Requires-Dist: treq
Requires-Dist: twisted[tls]
Requires-Dist: typeguard
